darwinex_ticks
