Metadata-Version: 1.0
Name: Darwinex-ticks
Version: 0.1.4
Summary: Darwinex tick data downloader Python API
Home-page: https://github.com/paduel/darwinex_ticks
Author: Paduel
Author-email: paduel@gmail.com
License: MIT
Platform: UNKNOWN
